{
  "definitions": [
    {
      "title": "Top Picks Cards",
      "id": "feature-product-cards",
      "plugins": {
        "xwalk": {
          "page": {
            "resourceType": "core/franklin/components/block/v1/block",
            "template": {
              "name": "Top Picks Cards",
              "filter": "feature-product-cards"
            }
          }
        }
      }
    },
    {
      "title": "Top Picks Card",
      "id": "feature-product-card",
      "plugins": {
        "xwalk": {
          "page": {
            "resourceType": "core/franklin/components/block/v1/block/item",
            "template": {
              "name": "Top Picks Card",
              "model": "feature-product-card"
            }
          }
        }
      }
    }
  ],
  "models": [
    {
      "id": "feature-product-card",
      "fields": [
        {
          "component": "reference",
          "valueType": "string",
          "name": "image",
          "label": "Product Image",
          "description": "Upload or select a product image",
          "multi": false
        },
        {
          "component": "text",
          "valueType": "string",
          "name": "label",
          "label": "Product Label/Category",
          "description": "Small label text (e.g., 'Top picks', 'Featured', etc.)",
          "value": "Top picks"
        },
        {
          "component": "text",
          "valueType": "string",
          "name": "title",
          "label": "Product Title",
          "description": "Main product title or name",
          "value": "",
          "validation": {
            "required": true
          }
        },
        {
          "component": "text",
          "valueType": "string",
          "name": "ctaLinkName",
          "label": "CTA Link Name",
          "description": "Text for the call-to-action button (e.g., 'View configs', 'Learn more')",
          "value": "View configs"
        },
        {
          "component": "aem-content",
          "name": "link",
          "label": "Call-to-Action Link",
          "description": "Link URL for the call-to-action",
          "valueType": "string"
        }
      ]
    }
  ],
  "filters": [
    {
      "id": "feature-product-cards",
      "components": [
        "feature-product-card"
      ]
    }
  ]
}
